webdav3_cli/Configuration.py
webdav3_cli/__init__.py
webdav3_cli/cli.py
webdav3_cli/cli_parsers/ArgumentParser.py
webdav3_cli/cli_parsers/ConfigCommandParser.py
webdav3_cli/cli_parsers/DebugParser.py
webdav3_cli/cli_parsers/ListCommandParser.py
webdav3_cli/cli_parsers/UploadCommandParser.py
webdav3_cli/cli_parsers/__init__.py
webdav3_cli/webdav3client_wrapper.py
webdav3_cli-1.0.0.post0.dist-info/METADATA
webdav3_cli-1.0.0.post0.dist-info/WHEEL
webdav3_cli-1.0.0.post0.dist-info/entry_points.txt
webdav3_cli-1.0.0.post0.dist-info/RECORD
