Metadata-Version: 2.1
Name: webdav3-cli
Version: 1.0.0.post0
Summary: Command line interface for webdav3
Author: Nicholas Johnson
Author-email: nicholas.m.j@gmail.com
Requires-Python: >=3.9,<4.0
Classifier: Programming Language :: Python :: 3
Classifier: Programming Language :: Python :: 3.9
Classifier: Programming Language :: Python :: 3.10
Classifier: Programming Language :: Python :: 3.11
Requires-Dist: tomlkit (>=0.11.7,<0.12.0)
Requires-Dist: webdavclient3 (>=3.14.6,<4.0.0)
